{
  "$schema": "https://developer.microsoft.com/json-schemas/spfx-build/package-solution.schema.json",
  "solution": {
    "name": "event-calendar-wp-client-side-solution",
    "id": "da90053e-aaf5-4223-a87f-f68afc225d1e",
    "version": "1.0.0.0",
    "title": "WC - Events",
    "includeClientSideAssets": true,
    "skipFeatureDeployment": true,
    "isDomainIsolated": false,
    "developer": {
      "name": "W. Kevin Wolff, Wolff Creative",
      "websiteUrl": "",
      "privacyUrl": "",
      "termsOfUseUrl": "",
      "mpnId": "Undefined-1.22.2"
    },
    "metadata": {
      "shortDescription": {
        "default": "Display events from a SharePoint list in filmstrip, compact list, or calendar views."
      },
      "longDescription": {
        "default": "WC - Events web part displays events from any SharePoint list with configurable field mappings, filmstrip and compact list layouts, calendar view, and property pane controls for category, location, time, and image display."
      },
      "screenshotPaths": [],
      "videoUrl": "",
      "categories": []
    },
    "features": [
      {
        "title": "event-calendar-wp Feature",
        "description": "The feature that activates elements of the event-calendar-wp solution.",
        "id": "93d07827-2767-4096-8cb1-fef9828c11fd",
        "version": "1.0.0.0"
      }
    ]
  },
  "paths": {
    "zippedPackage": "solution/event-calendar-wp.sppkg"
  }
}
